{
  "fill" : {
    "automatic-gradient" : "display-p3:0.40038,0.39319,0.96783,1.00000"
  },
  "groups" : [
    {
      "layers" : [
        {
          "fill-specializations" : [
            {
              "value" : {
                "solid" : "display-p3:0.66075,0.72122,0.96783,1.00000"
              }
            },
            {
              "appearance" : "dark",
              "value" : {
                "solid" : "display-p3:0.40186,0.39258,0.96484,1.00000"
              }
            }
          ],
          "image-name" : "􀒷.svg",
          "name" : "􀒷",
          "position" : {
            "scale" : 4,
            "translation-in-points" : [
              0,
              0
            ]
          }
        }
      ],
      "shadow" : {
        "kind" : "neutral",
        "opacity" : 0.5
      },
      "translucency" : {
        "enabled" : true,
        "value" : 0.5
      }
    }
  ],
  "supported-platforms" : {
    "circles" : [
      "watchOS"
    ],
    "squares" : "shared"
  }
}